[
  {
    "id": "978-1-878356-90-1",
    "color": "purple",
    "size": ["XL", "M"],
    "rating": 4,
    "brand": "Considine, Kihn and Ritchie",
    "product": "Gorgeous Metal Chips",
    "price": "986.00",
    "desc": "The slim & simple Maple Gaming Keyboard from Dev Byte comes with a sleek body and 7- Color RGB LED Back-lighting for smart functionality",
    "category": "Tuna",
    "fullName": "Shania",
    "image": "https://loremflickr.com/640/480/clothing?lock=8904084264321024"
  },
  {
    "id": "978-0-7979-0611-2",
    "color": "plum",
    "size": ["L"],
    "rating": 2,
    "brand": "Emmerich - Effertz",
    "product": "Elegant Wooden Car",
    "price": "880.00",
    "desc": "The Football Is Good For Training And Recreational Purposes",
    "category": "Salad",
    "fullName": "Nathanial",
    "image": "https://loremflickr.com/640/480/clothing?lock=8009015516725244"
  },
  {
    "id": "978-1-197-98688-9",
    "color": "maroon",
    "size": ["L"],
    "rating": 2,
    "brand": "Emard - Leffler",
    "product": "Electronic Steel Tuna",
    "price": "97.00",
    "desc": "Boston's most advanced compression wear technology increases muscle oxygenation, stabilizes active muscles",
    "category": "Chips",
    "fullName": "Freda",
    "image": "https://loremflickr.com/640/480/clothing?lock=6379848312291328"
  },
  {
    "id": "978-0-437-33919-5",
    "color": "turquoise",
    "size": ["S", "L", "M", "XL"],
    "rating": 5,
    "brand": "Balistreri LLC",
    "product": "Handmade Wooden Bike",
    "price": "839.00",
    "desc": "Carbonite web goalkeeper gloves are ergonomically designed to give easy fit",
    "category": "Shirt",
    "fullName": "Katlynn",
    "image": "https://loremflickr.com/640/480/clothing?lock=5720438552395776"
  },
  {
    "id": "978-0-251-28961-4",
    "color": "plum",
    "size": ["L", "XL", "M"],
    "rating": 1,
    "brand": "Adams - Rutherford",
    "product": "Sleek Cotton Bacon",
    "price": "273.00",
    "desc": "The slim & simple Maple Gaming Keyboard from Dev Byte comes with a sleek body and 7- Color RGB LED Back-lighting for smart functionality",
    "category": "Bike",
    "fullName": "Janelle",
    "image": "https://loremflickr.com/640/480/clothing?lock=759274907107328"
  },
  {
    "id": "978-1-7253-6242-0",
    "color": "pink",
    "size": ["L", "S", "XL", "M"],
    "rating": 5,
    "brand": "Keeling LLC",
    "product": "Luxurious Soft Table",
    "price": "957.00",
    "desc": "The Football Is Good For Training And Recreational Purposes",
    "category": "Hat",
    "fullName": "Alva",
    "image": "https://loremflickr.com/640/480/clothing?lock=3198498153431040"
  },
  {
    "id": "978-1-56910-740-9",
    "color": "plum",
    "size": ["XL", "S", "L", "M"],
    "rating": 2,
    "brand": "Zboncak Inc",
    "product": "Refined Metal Tuna",
    "price": "687.00",
    "desc": "Carbonite web goalkeeper gloves are ergonomically designed to give easy fit",
    "category": "Mouse",
    "fullName": "Alfredo",
    "image": "https://loremflickr.com/640/480/clothing?lock=2647667295387644"
  },
  {
    "id": "978-1-82231-529-9",
    "color": "silver",
    "size": ["L", "M", "S", "XL"],
    "rating": 5,
    "brand": "Bosco, Thiel and Herzog",
    "product": "Oriental Bronze Pants",
    "price": "757.00",
    "desc": "The Apollotech B340 is an affordable wireless mouse with reliable connectivity, 12 months battery life and modern design",
    "category": "Bike",
    "fullName": "Marguerite",
    "image": "https://loremflickr.com/640/480/clothing?lock=598814983454729"
  },
  {
    "id": "978-0-433-62755-5",
    "color": "tan",
    "size": ["L", "M", "XL"],
    "rating": 4,
    "brand": "Kunze and Sons",
    "product": "Awesome Wooden Towels",
    "price": "28.00",
    "desc": "The automobile layout consists of a front-engine design, with transaxle-type transmissions mounted at the rear of the engine and four wheel drive",
    "category": "Gloves",
    "fullName": "Eve",
    "image": "https://loremflickr.com/640/480/clothing?lock=6308242904842240"
  },
  {
    "id": "978-1-56599-889-6",
    "color": "gold",
    "size": ["M"],
    "rating": 2,
    "brand": "Kub Inc",
    "product": "Ergonomic Frozen Pizza",
    "price": "211.00",
    "desc": "The slim & simple Maple Gaming Keyboard from Dev Byte comes with a sleek body and 7- Color RGB LED Back-lighting for smart functionality",
    "category": "Salad",
    "fullName": "Alessandra",
    "image": "https://loremflickr.com/640/480/clothing?lock=3005164011126784"
  },
  {
    "id": "978-1-64992-593-0",
    "color": "plum",
    "size": ["XL"],
    "rating": 5,
    "brand": "Nienow LLC",
    "product": "Practical Concrete Chicken",
    "price": "774.00",
    "desc": "The slim & simple Maple Gaming Keyboard from Dev Byte comes with a sleek body and 7- Color RGB LED Back-lighting for smart functionality",
    "category": "Chips",
    "fullName": "Winona",
    "image": "https://loremflickr.com/640/480/clothing?lock=3469328567500800"
  },
  {
    "id": "978-1-921985-25-6",
    "color": "lime",
    "size": ["S", "XL"],
    "rating": 4,
    "brand": "Botsford - Monahan",
    "product": "Elegant Soft Fish",
    "price": "814.00",
    "desc": "The beautiful range of Apple Naturalé that has an exciting mix of natural ingredients. With the Goodness of 100% Natural Ingredients",
    "category": "Ball",
    "fullName": "Domenick",
    "image": "https://loremflickr.com/640/480/clothing?lock=7568809286172672"
  },
  {
    "id": "978-0-464-94087-6",
    "color": "ivory",
    "size": ["L"],
    "rating": 1,
    "brand": "Krajcik - Borer",
    "product": "Luxurious Cotton Bike",
    "price": "64.00",
    "desc": "Ergonomic executive chair upholstered in bonded black leather and PVC padded seat and back for all-day comfort and support",
    "category": "Chair",
    "fullName": "Emely",
    "image": "https://loremflickr.com/640/480/clothing?lock=6519235314450432"
  },
  {
    "id": "978-1-899512-48-5",
    "color": "purple",
    "size": ["XL", "M", "S"],
    "rating": 3,
    "brand": "Reynolds LLC",
    "product": "Oriental Frozen Table",
    "price": "667.00",
    "desc": "The Apollotech B340 is an affordable wireless mouse with reliable connectivity, 12 months battery life and modern design",
    "category": "Tuna",
    "fullName": "Adrain",
    "image": "https://loremflickr.com/640/480/clothing?lock=6255674101071872"
  },
  {
    "id": "978-1-6929-8042-9",
    "color": "orchid",
    "size": ["M", "S"],
    "rating": 1,
    "brand": "Mitchell - Hoeger",
    "product": "Tasty Wooden Computer",
    "price": "654.00",
    "desc": "The Football Is Good For Training And Recreational Purposes",
    "category": "Keyboard",
    "fullName": "Maurine",
    "image": "https://loremflickr.com/640/480/clothing?lock=3949398899818496"
  },
  {
    "id": "978-1-5331-9618-7",
    "color": "salmon",
    "size": ["M", "XL", "L"],
    "rating": 3,
    "brand": "Cremin, Kulas and Mitchell",
    "product": "Refined Steel Shirt",
    "price": "258.00",
    "desc": "New ABC 13 9370, 13.3, 5th Gen CoreA5-8250U, 8GB RAM, 256GB SSD, power UHD Graphics, OS 10 Home, OS Office A & J 2016",
    "category": "Hat",
    "fullName": "Maryjane",
    "image": "https://loremflickr.com/640/480/clothing?lock=3378574295826432"
  },
  {
    "id": "978-1-0836-0186-5",
    "color": "tan",
    "size": ["L", "M", "XL", "S"],
    "rating": 3,
    "brand": "Towne - Keeling",
    "product": "Tasty Frozen Soap",
    "price": "91.00",
    "desc": "The Apollotech B340 is an affordable wireless mouse with reliable connectivity, 12 months battery life and modern design",
    "category": "Mouse",
    "fullName": "Marian",
    "image": "https://loremflickr.com/640/480/clothing?lock=3221506368733184"
  },
  {
    "id": "978-0-7007-0571-9",
    "color": "orchid",
    "size": ["M", "S", "L"],
    "rating": 4,
    "brand": "Hamill - Jacobson",
    "product": "Licensed Soft Chips",
    "price": "766.00",
    "desc": "New range of formal shirts are designed keeping you in mind. With fits and styling that will make you stand apart",
    "category": "Bacon",
    "fullName": "Kenna",
    "image": "https://loremflickr.com/640/480/clothing?lock=392329015853056"
  },
  {
    "id": "978-1-56612-193-4",
    "color": "red",
    "size": ["S", "XL"],
    "rating": 5,
    "brand": "Pollich - Cruickshank",
    "product": "Licensed Concrete Table",
    "price": "945.00",
    "desc": "New ABC 13 9370, 13.3, 5th Gen CoreA5-8250U, 8GB RAM, 256GB SSD, power UHD Graphics, OS 10 Home, OS Office A & J 2016",
    "category": "Bike",
    "fullName": "Dagmar",
    "image": "https://loremflickr.com/640/480/clothing?lock=6794375921139712"
  },
  {
    "id": "978-0-393-16840-2",
    "color": "salmon",
    "size": ["S", "M", "XL", "L"],
    "rating": 1,
    "brand": "Crona, Shields and Champlin",
    "product": "Refined Frozen Soap",
    "price": "264.00",
    "desc": "New ABC 13 9370, 13.3, 5th Gen CoreA5-8250U, 8GB RAM, 256GB SSD, power UHD Graphics, OS 10 Home, OS Office A & J 2016",
    "category": "Tuna",
    "fullName": "Antonio",
    "image": "https://loremflickr.com/640/480/clothing?lock=6324961016807424"
  },
  {
    "id": "978-0-464-48894-1",
    "color": "purple",
    "size": ["M"],
    "rating": 2,
    "brand": "Kuhlman, Raynor and Mayer",
    "product": "Tasty Metal Bike",
    "price": "167.00",
    "desc": "The Nagasaki Lander is the trademarked name of several series of Nagasaki sport bikes, that started with the 1984 ABC800J",
    "category": "Pants",
    "fullName": "Camden",
    "image": "https://loremflickr.com/640/480/clothing?lock=4278585623838720"
  },
  {
    "id": "978-0-8231-8208-4",
    "color": "mint green",
    "size": ["XL"],
    "rating": 2,
    "brand": "Halvorson, Green and Kreiger",
    "product": "Intelligent Cotton Car",
    "price": "111.00",
    "desc": "The beautiful range of Apple Naturalé that has an exciting mix of natural ingredients. With the Goodness of 100% Natural Ingredients",
    "category": "Mouse",
    "fullName": "Efrain",
    "image": "https://loremflickr.com/640/480/clothing?lock=1492868266983424"
  },
  {
    "id": "978-0-457-76734-3",
    "color": "lavender",
    "size": ["M", "XL"],
    "rating": 5,
    "brand": "Prosacco, Pfeffer and Kerluke",
    "product": "Incredible Bronze Shoes",
    "price": "783.00",
    "desc": "New ABC 13 9370, 13.3, 5th Gen CoreA5-8250U, 8GB RAM, 256GB SSD, power UHD Graphics, OS 10 Home, OS Office A & J 2016",
    "category": "Keyboard",
    "fullName": "Rubie",
    "image": "https://loremflickr.com/640/480/clothing?lock=435550536335360"
  },
  {
    "id": "978-1-63020-489-1",
    "color": "white",
    "size": ["XL"],
    "rating": 3,
    "brand": "Quitzon - Lind",
    "product": "Elegant Cotton Table",
    "price": "357.00",
    "desc": "New ABC 13 9370, 13.3, 5th Gen CoreA5-8250U, 8GB RAM, 256GB SSD, power UHD Graphics, OS 10 Home, OS Office A & J 2016",
    "category": "Cheese",
    "fullName": "Lizzie",
    "image": "https://loremflickr.com/640/480/clothing?lock=532543361253376"
  },
  {
    "id": "978-0-441-21844-8",
    "color": "red",
    "size": ["S", "M", "L", "XL"],
    "rating": 3,
    "brand": "Heidenreich LLC",
    "product": "Rustic Wooden Chicken",
    "price": "150.00",
    "desc": "New range of formal shirts are designed keeping you in mind. With fits and styling that will make you stand apart",
    "category": "Bike",
    "fullName": "Alexane",
    "image": "https://loremflickr.com/640/480/clothing?lock=1347425268662272"
  },
  {
    "id": "978-1-02-643504-5",
    "color": "mint green",
    "size": ["XL", "S"],
    "rating": 5,
    "brand": "McDermott and Sons",
    "product": "Recycled Granite Keyboard",
    "price": "314.00",
    "desc": "New range of formal shirts are designed keeping you in mind. With fits and styling that will make you stand apart",
    "category": "Soap",
    "fullName": "Terrill",
    "image": "https://loremflickr.com/640/480/clothing?lock=2295050065149952"
  },
  {
    "id": "978-0-921828-29-7",
    "color": "indigo",
    "size": ["S", "L", "XL"],
    "rating": 4,
    "brand": "Weissnat - Emard",
    "product": "Incredible Steel Soap",
    "price": "843.00",
    "desc": "The Football Is Good For Training And Recreational Purposes",
    "category": "Gloves",
    "fullName": "Raheem",
    "image": "https://loremflickr.com/640/480/clothing?lock=5581783080894464"
  },
  {
    "id": "978-0-7521-5217-2",
    "color": "green",
    "size": ["L", "S", "XL"],
    "rating": 1,
    "brand": "Goyette, Armstrong and Wilderman",
    "product": "Handmade Cotton Pants",
    "price": "277.00",
    "desc": "The automobile layout consists of a front-engine design, with transaxle-type transmissions mounted at the rear of the engine and four wheel drive",
    "category": "Ball",
    "fullName": "Bret",
    "image": "https://loremflickr.com/640/480/clothing?lock=4028728252301312"
  },
  {
    "id": "978-1-343-49216-5",
    "color": "violet",
    "size": ["M", "L"],
    "rating": 4,
    "brand": "Hackett and Sons",
    "product": "Gorgeous Wooden Soap",
    "price": "849.00",
    "desc": "The Apollotech B340 is an affordable wireless mouse with reliable connectivity, 12 months battery life and modern design",
    "category": "Shirt",
    "fullName": "Zita",
    "image": "https://loremflickr.com/640/480/clothing?lock=1366822762840064"
  },
  {
    "id": "978-0-7151-6520-1",
    "color": "orchid",
    "size": ["S", "XL"],
    "rating": 1,
    "brand": "Lueilwitz Inc",
    "product": "Bespoke Bronze Ball",
    "price": "652.00",
    "desc": "Ergonomic executive chair upholstered in bonded black leather and PVC padded seat and back for all-day comfort and support",
    "category": "Tuna",
    "fullName": "Virginie",
    "image": "https://loremflickr.com/640/480/clothing?lock=602187644272640"
  },
  {
    "id": "978-1-967914-92-0",
    "color": "yellow",
    "size": ["XL", "S"],
    "rating": 2,
    "brand": "Miller Group",
    "product": "Handmade Steel Chicken",
    "price": "341.00",
    "desc": "Boston's most advanced compression wear technology increases muscle oxygenation, stabilizes active muscles",
    "category": "Car",
    "fullName": "Ariel",
    "image": "https://loremflickr.com/640/480/clothing?lock=6852862235639808"
  },
  {
    "id": "978-1-959109-57-0",
    "color": "orange",
    "size": ["L", "S", "XL"],
    "rating": 4,
    "brand": "Graham, Fisher and Nicolas",
    "product": "Luxurious Concrete Table",
    "price": "268.00",
    "desc": "Boston's most advanced compression wear technology increases muscle oxygenation, stabilizes active muscles",
    "category": "Towels",
    "fullName": "Lottie",
    "image": "https://loremflickr.com/640/480/clothing?lock=585430669983744"
  },
  {
    "id": "978-0-504-32004-0",
    "color": "sky blue",
    "size": ["S", "M", "XL"],
    "rating": 2,
    "brand": "Dare, Fadel and Block",
    "product": "Rustic Frozen Gloves",
    "price": "104.00",
    "desc": "Ergonomic executive chair upholstered in bonded black leather and PVC padded seat and back for all-day comfort and support",
    "category": "Bike",
    "fullName": "Ulices",
    "image": "https://loremflickr.com/640/480/clothing?lock=6926240134987776"
  },
  {
    "id": "978-1-80892-670-9",
    "color": "blue",
    "size": ["S", "M", "L", "XL"],
    "rating": 5,
    "brand": "Wiegand - Dibbert",
    "product": "Electronic Wooden Bike",
    "price": "300.00",
    "desc": "Carbonite web goalkeeper gloves are ergonomically designed to give easy fit",
    "category": "Keyboard",
    "fullName": "Monique",
    "image": "https://loremflickr.com/640/480/clothing?lock=2020136552759296"
  },
  {
    "id": "978-1-76777-807-4",
    "color": "orange",
    "size": ["L", "M"],
    "rating": 5,
    "brand": "Treutel, Hintz and Weber",
    "product": "Recycled Metal Sausages",
    "price": "120.00",
    "desc": "Boston's most advanced compression wear technology increases muscle oxygenation, stabilizes active muscles",
    "category": "Chair",
    "fullName": "Brice",
    "image": "https://loremflickr.com/640/480/clothing?lock=7209391570812928"
  },
  {
    "id": "978-1-186-50793-4",
    "color": "sky blue",
    "size": ["M", "S"],
    "rating": 5,
    "brand": "Bins Inc",
    "product": "Sleek Metal Tuna",
    "price": "483.00",
    "desc": "The slim & simple Maple Gaming Keyboard from Dev Byte comes with a sleek body and 7- Color RGB LED Back-lighting for smart functionality",
    "category": "Table",
    "fullName": "Lera",
    "image": "https://loremflickr.com/640/480/clothing?lock=4385538916220928"
  },
  {
    "id": "978-1-218-45088-7",
    "color": "silver",
    "size": ["S", "L", "XL", "M"],
    "rating": 1,
    "brand": "Bergstrom - Howell",
    "product": "Recycled Metal Table",
    "price": "132.00",
    "desc": "The Nagasaki Lander is the trademarked name of several series of Nagasaki sport bikes, that started with the 1984 ABC800J",
    "category": "Mouse",
    "fullName": "Clifford",
    "image": "https://loremflickr.com/640/480/clothing?lock=941885252173824"
  },
  {
    "id": "978-0-401-47824-0",
    "color": "lavender",
    "size": ["S", "L"],
    "rating": 2,
    "brand": "Abshire, Douglas and Blanda",
    "product": "Awesome Metal Soap",
    "price": "704.00",
    "desc": "The Football Is Good For Training And Recreational Purposes",
    "category": "Gloves",
    "fullName": "Jayme",
    "image": "https://loremflickr.com/640/480/clothing?lock=4235866115407872"
  },
  {
    "id": "978-1-06-897342-0",
    "color": "azure",
    "size": ["M", "XL", "L"],
    "rating": 1,
    "brand": "Wintheiser - Pollich",
    "product": "Ergonomic Rubber Ball",
    "price": "964.00",
    "desc": "The slim & simple Maple Gaming Keyboard from Dev Byte comes with a sleek body and 7- Color RGB LED Back-lighting for smart functionality",
    "category": "Sausages",
    "fullName": "Marjolaine",
    "image": "https://loremflickr.com/640/480/clothing?lock=5993498983530496"
  },
  {
    "id": "978-1-02-255801-4",
    "color": "purple",
    "size": ["M"],
    "rating": 4,
    "brand": "Bartoletti, Gerlach and Donnelly",
    "product": "Refined Rubber Chips",
    "price": "772.00",
    "desc": "The Apollotech B340 is an affordable wireless mouse with reliable connectivity, 12 months battery life and modern design",
    "category": "Towels",
    "fullName": "Mustafa",
    "image": "https://loremflickr.com/640/480/clothing?lock=3207270064193536"
  },
  {
    "id": "978-1-55561-520-8",
    "color": "olive",
    "size": ["XL"],
    "rating": 2,
    "brand": "Towne - Nikolaus",
    "product": "Tasty Frozen Table",
    "price": "560.00",
    "desc": "The Apollotech B340 is an affordable wireless mouse with reliable connectivity, 12 months battery life and modern design",
    "category": "Tuna",
    "fullName": "Davin",
    "image": "https://loremflickr.com/640/480/clothing?lock=2982291817103360"
  },
  {
    "id": "978-0-10-568708-5",
    "color": "plum",
    "size": ["L", "M"],
    "rating": 2,
    "brand": "Jacobi, Barton and Oberbrunner",
    "product": "Handmade Bronze Bacon",
    "price": "78.00",
    "desc": "Andy shoes are designed to keeping in mind durability as well as trends, the most stylish range of shoes & sandals",
    "category": "Fish",
    "fullName": "Lottie",
    "image": "https://loremflickr.com/640/480/clothing?lock=7654410312220672"
  },
  {
    "id": "978-1-6540-1531-2",
    "color": "olive",
    "size": ["XL", "L", "S"],
    "rating": 3,
    "brand": "Mraz Inc",
    "product": "Elegant Soft Shoes",
    "price": "992.00",
    "desc": "Andy shoes are designed to keeping in mind durability as well as trends, the most stylish range of shoes & sandals",
    "category": "Ball",
    "fullName": "Conner",
    "image": "https://loremflickr.com/640/480/clothing?lock=806256489005056"
  },
  {
    "id": "978-0-9560480-7-3",
    "color": "orange",
    "size": ["XL"],
    "rating": 3,
    "brand": "Kovacek Inc",
    "product": "Unbranded Cotton Chips",
    "price": "922.00",
    "desc": "Ergonomic executive chair upholstered in bonded black leather and PVC padded seat and back for all-day comfort and support",
    "category": "Salad",
    "fullName": "Maxime",
    "image": "https://loremflickr.com/640/480/clothing?lock=98340836474880"
  },
  {
    "id": "978-1-925635-37-9",
    "color": "white",
    "size": ["XL"],
    "rating": 4,
    "brand": "Considine - Leffler",
    "product": "Intelligent Bronze Chicken",
    "price": "875.00",
    "desc": "The Football Is Good For Training And Recreational Purposes",
    "category": "Shirt",
    "fullName": "Herman",
    "image": "https://loremflickr.com/640/480/clothing?lock=7976404866039808"
  },
  {
    "id": "978-1-62379-157-5",
    "color": "maroon",
    "size": ["L"],
    "rating": 5,
    "brand": "Carter - Botsford",
    "product": "Elegant Frozen Hat",
    "price": "420.00",
    "desc": "Boston's most advanced compression wear technology increases muscle oxygenation, stabilizes active muscles",
    "category": "Pizza",
    "fullName": "Fae",
    "image": "https://loremflickr.com/640/480/clothing?lock=7283593906749440"
  },
  {
    "id": "978-0-10-191938-8",
    "color": "lavender",
    "size": ["S"],
    "rating": 4,
    "brand": "O'Kon, Walter and Schultz",
    "product": "Electronic Concrete Keyboard",
    "price": "183.00",
    "desc": "Boston's most advanced compression wear technology increases muscle oxygenation, stabilizes active muscles",
    "category": "Keyboard",
    "fullName": "Schuyler",
    "image": "https://loremflickr.com/640/480/clothing?lock=63619263889408"
  },
  {
    "id": "978-0-565-30537-6",
    "color": "yellow",
    "size": ["M", "XL"],
    "rating": 5,
    "brand": "Gottlieb - Yundt",
    "product": "Sleek Soft Shoes",
    "price": "22.00",
    "desc": "Carbonite web goalkeeper gloves are ergonomically designed to give easy fit",
    "category": "Hat",
    "fullName": "Rasheed",
    "image": "https://loremflickr.com/640/480/clothing?lock=4431373758627840"
  },
  {
    "id": "978-1-949917-79-6",
    "color": "gold",
    "size": ["M", "S", "L", "XL"],
    "rating": 5,
    "brand": "Schroeder - Farrell",
    "product": "Generic Bronze Chips",
    "price": "45.00",
    "desc": "The automobile layout consists of a front-engine design, with transaxle-type transmissions mounted at the rear of the engine and four wheel drive",
    "category": "Chips",
    "fullName": "Woodrow",
    "image": "https://loremflickr.com/640/480/clothing?lock=7035960260820992"
  },
  {
    "id": "978-0-9910419-5-4",
    "color": "cyan",
    "size": ["L", "M"],
    "rating": 4,
    "brand": "MacGyver, Kassulke and Shields",
    "product": "Bespoke Steel Fish",
    "price": "446.00",
    "desc": "Boston's most advanced compression wear technology increases muscle oxygenation, stabilizes active muscles",
    "category": "Shoes",
    "fullName": "Mireya",
    "image": "https://loremflickr.com/640/480/clothing?lock=7525515621564416"
  },
  {
    "id": "978-1-5101-7590-7",
    "color": "orange",
    "size": ["S"],
    "rating": 3,
    "brand": "Corkery and Sons",
    "product": "Ergonomic Concrete Shirt",
    "price": "660.00",
    "desc": "The slim & simple Maple Gaming Keyboard from Dev Byte comes with a sleek body and 7- Color RGB LED Back-lighting for smart functionality",
    "category": "Hat",
    "fullName": "Patsy",
    "image": "https://loremflickr.com/640/480/clothing?lock=941281658273792"
  },
  {
    "id": "978-1-144-09876-4",
    "color": "turquoise",
    "size": ["XL"],
    "rating": 2,
    "brand": "Quitzon - Konopelski",
    "product": "Bespoke Frozen Chair",
    "price": "766.00",
    "desc": "Andy shoes are designed to keeping in mind durability as well as trends, the most stylish range of shoes & sandals",
    "category": "Chips",
    "fullName": "Nicholas",
    "image": "https://loremflickr.com/640/480/clothing?lock=7758365683875840"
  },
  {
    "id": "978-1-250-78317-2",
    "color": "sky blue",
    "size": ["XL"],
    "rating": 1,
    "brand": "O'Conner - Koch",
    "product": "Unbranded Plastic Pants",
    "price": "649.00",
    "desc": "The automobile layout consists of a front-engine design, with transaxle-type transmissions mounted at the rear of the engine and four wheel drive",
    "category": "Tuna",
    "fullName": "Luella",
    "image": "https://loremflickr.com/640/480/clothing?lock=8713706267475968"
  },
  {
    "id": "978-0-611-19589-0",
    "color": "magenta",
    "size": ["L", "S", "XL", "M"],
    "rating": 4,
    "brand": "Prosacco - Toy",
    "product": "Handcrafted Soft Chicken",
    "price": "795.00",
    "desc": "Ergonomic executive chair upholstered in bonded black leather and PVC padded seat and back for all-day comfort and support",
    "category": "Towels",
    "fullName": "Tobin",
    "image": "https://loremflickr.com/640/480/clothing?lock=4352186974732288"
  },
  {
    "id": "978-0-611-26319-3",
    "color": "lavender",
    "size": ["XL"],
    "rating": 3,
    "brand": "Sipes LLC",
    "product": "Awesome Soft Car",
    "price": "722.00",
    "desc": "Ergonomic executive chair upholstered in bonded black leather and PVC padded seat and back for all-day comfort and support",
    "category": "Cheese",
    "fullName": "Elisabeth",
    "image": "https://loremflickr.com/640/480/clothing?lock=2260585506930688"
  },
  {
    "id": "978-0-7495-4553-6",
    "color": "green",
    "size": ["M"],
    "rating": 5,
    "brand": "Murazik Group",
    "product": "Small Bronze Sausages",
    "price": "446.00",
    "desc": "New range of formal shirts are designed keeping you in mind. With fits and styling that will make you stand apart",
    "category": "Mouse",
    "fullName": "Myrtice",
    "image": "https://loremflickr.com/640/480/clothing?lock=4574559019728896"
  },
  {
    "id": "978-0-689-40483-2",
    "color": "ivory",
    "size": ["M", "S", "L"],
    "rating": 1,
    "brand": "Daugherty LLC",
    "product": "Electronic Cotton Chair",
    "price": "940.00",
    "desc": "New ABC 13 9370, 13.3, 5th Gen CoreA5-8250U, 8GB RAM, 256GB SSD, power UHD Graphics, OS 10 Home, OS Office A & J 2016",
    "category": "Salad",
    "fullName": "Fernando",
    "image": "https://loremflickr.com/640/480/clothing?lock=1578448956948480"
  },
  {
    "id": "978-0-443-80746-6",
    "color": "mint green",
    "size": ["XL", "M", "S", "L"],
    "rating": 2,
    "brand": "Weissnat - Haag",
    "product": "Luxurious Soft Sausages",
    "price": "686.00",
    "desc": "The slim & simple Maple Gaming Keyboard from Dev Byte comes with a sleek body and 7- Color RGB LED Back-lighting for smart functionality",
    "category": "Shoes",
    "fullName": "Tyree",
    "image": "https://loremflickr.com/640/480/clothing?lock=2682083577167872"
  },
  {
    "id": "978-0-541-76407-4",
    "color": "gold",
    "size": ["M", "L", "XL"],
    "rating": 5,
    "brand": "Mraz and Sons",
    "product": "Ergonomic Metal Ball",
    "price": "147.00",
    "desc": "Ergonomic executive chair upholstered in bonded black leather and PVC padded seat and back for all-day comfort and support",
    "category": "Salad",
    "fullName": "Craig",
    "image": "https://loremflickr.com/640/480/clothing?lock=310131411648512"
  },
  {
    "id": "978-1-5171-0850-2",
    "color": "ivory",
    "size": ["L", "XL", "S"],
    "rating": 4,
    "brand": "Gutkowski Inc",
    "product": "Licensed Plastic Computer",
    "price": "181.00",
    "desc": "The slim & simple Maple Gaming Keyboard from Dev Byte comes with a sleek body and 7- Color RGB LED Back-lighting for smart functionality",
    "category": "Ball",
    "fullName": "Alison",
    "image": "https://loremflickr.com/640/480/clothing?lock=268794305970176"
  },
  {
    "id": "978-1-876240-74-5",
    "color": "ivory",
    "size": ["XL", "S", "L", "M"],
    "rating": 4,
    "brand": "Wehner - Brakus",
    "product": "Fantastic Steel Keyboard",
    "price": "376.00",
    "desc": "Boston's most advanced compression wear technology increases muscle oxygenation, stabilizes active muscles",
    "category": "Hat",
    "fullName": "Hanna",
    "image": "https://loremflickr.com/640/480/clothing?lock=7317939210420224"
  },
  {
    "id": "978-0-458-03250-1",
    "color": "red",
    "size": ["S"],
    "rating": 2,
    "brand": "Schroeder, Gottlieb and Jones",
    "product": "Small Plastic Computer",
    "price": "229.00",
    "desc": "The Football Is Good For Training And Recreational Purposes",
    "category": "Pizza",
    "fullName": "Adeline",
    "image": "https://loremflickr.com/640/480/clothing?lock=7925114559528960"
  },
  {
    "id": "978-1-5172-7292-0",
    "color": "orange",
    "size": ["L", "M"],
    "rating": 2,
    "brand": "Mayert, Kling and Huel",
    "product": "Incredible Steel Pants",
    "price": "471.00",
    "desc": "The beautiful range of Apple Naturalé that has an exciting mix of natural ingredients. With the Goodness of 100% Natural Ingredients",
    "category": "Sausages",
    "fullName": "Axel",
    "image": "https://loremflickr.com/640/480/clothing?lock=7097383112409088"
  },
  {
    "id": "978-0-936771-69-4",
    "color": "ivory",
    "size": ["S"],
    "rating": 4,
    "brand": "Ziemann, Cummerata and King",
    "product": "Practical Rubber Tuna",
    "price": "52.00",
    "desc": "The automobile layout consists of a front-engine design, with transaxle-type transmissions mounted at the rear of the engine and four wheel drive",
    "category": "Table",
    "fullName": "Karina",
    "image": "https://loremflickr.com/640/480/clothing?lock=6417331697745920"
  },
  {
    "id": "978-1-715-57352-2",
    "color": "indigo",
    "size": ["L"],
    "rating": 3,
    "brand": "Kirlin - Hand",
    "product": "Tasty Fresh Pants",
    "price": "556.00",
    "desc": "The Football Is Good For Training And Recreational Purposes",
    "category": "Chips",
    "fullName": "Lura",
    "image": "https://loremflickr.com/640/480/clothing?lock=528115279331328"
  },
  {
    "id": "978-1-714-30433-2",
    "color": "lavender",
    "size": ["M", "XL", "S"],
    "rating": 5,
    "brand": "Bernier - Lind",
    "product": "Generic Rubber Gloves",
    "price": "894.00",
    "desc": "The Apollotech B340 is an affordable wireless mouse with reliable connectivity, 12 months battery life and modern design",
    "category": "Bacon",
    "fullName": "Larissa",
    "image": "https://loremflickr.com/640/480/clothing?lock=4389439264522240"
  },
  {
    "id": "978-0-8303-0248-2",
    "color": "teal",
    "size": ["L", "XL", "S", "M"],
    "rating": 1,
    "brand": "Leffler Group",
    "product": "Licensed Steel Tuna",
    "price": "177.00",
    "desc": "Boston's most advanced compression wear technology increases muscle oxygenation, stabilizes active muscles",
    "category": "Car",
    "fullName": "Kayla",
    "image": "https://loremflickr.com/640/480/clothing?lock=1105734773243904"
  },
  {
    "id": "978-0-356-49617-7",
    "color": "orange",
    "size": ["S"],
    "rating": 5,
    "brand": "Kiehn Group",
    "product": "Practical Fresh Table",
    "price": "487.00",
    "desc": "The Apollotech B340 is an affordable wireless mouse with reliable connectivity, 12 months battery life and modern design",
    "category": "Pizza",
    "fullName": "Katelyn",
    "image": "https://loremflickr.com/640/480/clothing?lock=2555592537276416"
  },
  {
    "id": "978-1-961097-57-5",
    "color": "white",
    "size": ["S"],
    "rating": 5,
    "brand": "Goyette Group",
    "product": "Handmade Soft Car",
    "price": "671.00",
    "desc": "New range of formal shirts are designed keeping you in mind. With fits and styling that will make you stand apart",
    "category": "Hat",
    "fullName": "Hollis",
    "image": "https://loremflickr.com/640/480/clothing?lock=8596376592056320"
  },
  {
    "id": "978-1-228-70936-4",
    "color": "plum",
    "size": ["S", "M"],
    "rating": 2,
    "brand": "Torp - Hackett",
    "product": "Recycled Plastic Tuna",
    "price": "901.00",
    "desc": "Boston's most advanced compression wear technology increases muscle oxygenation, stabilizes active muscles",
    "category": "Mouse",
    "fullName": "Winfield",
    "image": "https://loremflickr.com/640/480/clothing?lock=2826302174265344"
  },
  {
    "id": "978-1-245-88941-4",
    "color": "cyan",
    "size": ["M", "XL"],
    "rating": 3,
    "brand": "Bruen LLC",
    "product": "Bespoke Steel Chips",
    "price": "144.00",
    "desc": "New range of formal shirts are designed keeping you in mind. With fits and styling that will make you stand apart",
    "category": "Salad",
    "fullName": "Frieda",
    "image": "https://loremflickr.com/640/480/clothing?lock=1960030228185088"
  },
  {
    "id": "978-0-405-03986-7",
    "color": "plum",
    "size": ["S", "M", "L", "XL"],
    "rating": 1,
    "brand": "Schmeler LLC",
    "product": "Unbranded Plastic Chicken",
    "price": "358.00",
    "desc": "New ABC 13 9370, 13.3, 5th Gen CoreA5-8250U, 8GB RAM, 256GB SSD, power UHD Graphics, OS 10 Home, OS Office A & J 2016",
    "category": "Shoes",
    "fullName": "Beulah",
    "image": "https://loremflickr.com/640/480/clothing?lock=6037399373086720"
  },
  {
    "id": "978-0-551-55386-6",
    "color": "magenta",
    "size": ["XL", "M"],
    "rating": 4,
    "brand": "Hammes - Schmeler",
    "product": "Refined Metal Keyboard",
    "price": "850.00",
    "desc": "The slim & simple Maple Gaming Keyboard from Dev Byte comes with a sleek body and 7- Color RGB LED Back-lighting for smart functionality",
    "category": "Mouse",
    "fullName": "Adrianna",
    "image": "https://loremflickr.com/640/480/clothing?lock=1301318232702976"
  },
  {
    "id": "978-0-7439-9909-0",
    "color": "fuchsia",
    "size": ["S", "M", "XL", "L"],
    "rating": 2,
    "brand": "Hamill, Ortiz and Boyer",
    "product": "Practical Metal Computer",
    "price": "258.00",
    "desc": "Andy shoes are designed to keeping in mind durability as well as trends, the most stylish range of shoes & sandals",
    "category": "Sausages",
    "fullName": "Yasmine",
    "image": "https://loremflickr.com/640/480/clothing?lock=369766510362624"
  },
  {
    "id": "978-1-872911-65-6",
    "color": "grey",
    "size": ["L"],
    "rating": 5,
    "brand": "Wiza, Kuhn and Rutherford",
    "product": "Electronic Cotton Cheese",
    "price": "247.00",
    "desc": "Boston's most advanced compression wear technology increases muscle oxygenation, stabilizes active muscles",
    "category": "Sausages",
    "fullName": "Kamren",
    "image": "https://loremflickr.com/640/480/clothing?lock=7291015201292288"
  },
  {
    "id": "978-0-257-12208-3",
    "color": "olive",
    "size": ["L"],
    "rating": 4,
    "brand": "Harris - Robel",
    "product": "Tasty Fresh Hat",
    "price": "523.00",
    "desc": "The Football Is Good For Training And Recreational Purposes",
    "category": "Cheese",
    "fullName": "Gerard",
    "image": "https://loremflickr.com/640/480/clothing?lock=5378639958900736"
  },
  {
    "id": "978-0-09-944207-3",
    "color": "orchid",
    "size": ["L", "S"],
    "rating": 2,
    "brand": "Koepp - Stark",
    "product": "Handcrafted Cotton Gloves",
    "price": "71.00",
    "desc": "The Nagasaki Lander is the trademarked name of several series of Nagasaki sport bikes, that started with the 1984 ABC800J",
    "category": "Car",
    "fullName": "Luigi",
    "image": "https://loremflickr.com/640/480/clothing?lock=1372551884308480"
  },
  {
    "id": "978-1-56381-689-5",
    "color": "grey",
    "size": ["M", "S", "XL", "L"],
    "rating": 1,
    "brand": "Mosciski - Schroeder",
    "product": "Recycled Bronze Chips",
    "price": "558.00",
    "desc": "Andy shoes are designed to keeping in mind durability as well as trends, the most stylish range of shoes & sandals",
    "category": "Towels",
    "fullName": "Chelsie",
    "image": "https://loremflickr.com/640/480/clothing?lock=6707638448422912"
  },
  {
    "id": "978-0-8203-8079-7",
    "color": "sky blue",
    "size": ["S"],
    "rating": 5,
    "brand": "Haley, Harvey and Willms",
    "product": "Fantastic Steel Bacon",
    "price": "751.00",
    "desc": "The automobile layout consists of a front-engine design, with transaxle-type transmissions mounted at the rear of the engine and four wheel drive",
    "category": "Computer",
    "fullName": "Rasheed",
    "image": "https://loremflickr.com/640/480/clothing?lock=5039847265796096"
  },
  {
    "id": "978-0-04-692641-0",
    "color": "azure",
    "size": ["S", "L", "XL", "M"],
    "rating": 1,
    "brand": "Carter LLC",
    "product": "Unbranded Concrete Shirt",
    "price": "314.00",
    "desc": "The Nagasaki Lander is the trademarked name of several series of Nagasaki sport bikes, that started with the 1984 ABC800J",
    "category": "Computer",
    "fullName": "Helga",
    "image": "https://loremflickr.com/640/480/clothing?lock=4091122301272064"
  },
  {
    "id": "978-1-05-556279-8",
    "color": "lavender",
    "size": ["S", "L", "M"],
    "rating": 1,
    "brand": "Zulauf and Sons",
    "product": "Elegant Steel Chips",
    "price": "647.00",
    "desc": "New ABC 13 9370, 13.3, 5th Gen CoreA5-8250U, 8GB RAM, 256GB SSD, power UHD Graphics, OS 10 Home, OS Office A & J 2016",
    "category": "Chips",
    "fullName": "Daija",
    "image": "https://loremflickr.com/640/480/clothing?lock=1301808355999744"
  },
  {
    "id": "978-0-572-25977-8",
    "color": "cyan",
    "size": ["M", "L"],
    "rating": 1,
    "brand": "Boyer, Windler and Rolfson",
    "product": "Incredible Concrete Keyboard",
    "price": "763.00",
    "desc": "The slim & simple Maple Gaming Keyboard from Dev Byte comes with a sleek body and 7- Color RGB LED Back-lighting for smart functionality",
    "category": "Cheese",
    "fullName": "Samson",
    "image": "https://loremflickr.com/640/480/clothing?lock=8890164409532416"
  },
  {
    "id": "978-1-242-36674-1",
    "color": "mint green",
    "size": ["M", "XL"],
    "rating": 2,
    "brand": "Ratke - Beahan",
    "product": "Tasty Concrete Gloves",
    "price": "845.00",
    "desc": "Boston's most advanced compression wear technology increases muscle oxygenation, stabilizes active muscles",
    "category": "Shoes",
    "fullName": "Cathryn",
    "image": "https://loremflickr.com/640/480/clothing?lock=4718077763649536"
  },
  {
    "id": "978-1-0873-8797-0",
    "color": "ivory",
    "size": ["XL", "M", "L", "S"],
    "rating": 3,
    "brand": "Runte LLC",
    "product": "Awesome Plastic Salad",
    "price": "72.00",
    "desc": "The Nagasaki Lander is the trademarked name of several series of Nagasaki sport bikes, that started with the 1984 ABC800J",
    "category": "Gloves",
    "fullName": "Dee",
    "image": "https://loremflickr.com/640/480/clothing?lock=4198755523887104"
  },
  {
    "id": "978-0-604-59284-2",
    "color": "teal",
    "size": ["XL", "M", "L", "S"],
    "rating": 5,
    "brand": "Nienow Group",
    "product": "Sleek Granite Table",
    "price": "199.00",
    "desc": "The Apollotech B340 is an affordable wireless mouse with reliable connectivity, 12 months battery life and modern design",
    "category": "Fish",
    "fullName": "Domenick",
    "image": "https://loremflickr.com/640/480/clothing?lock=7637010772656128"
  },
  {
    "id": "978-0-947609-47-4",
    "color": "violet",
    "size": ["XL", "M", "S"],
    "rating": 4,
    "brand": "Schroeder, Jacobi and Monahan",
    "product": "Incredible Cotton Mouse",
    "price": "720.00",
    "desc": "New range of formal shirts are designed keeping you in mind. With fits and styling that will make you stand apart",
    "category": "Shoes",
    "fullName": "Luis",
    "image": "https://loremflickr.com/640/480/clothing?lock=7668077799931904"
  },
  {
    "id": "978-1-208-16200-4",
    "color": "blue",
    "size": ["M", "S", "L", "XL"],
    "rating": 3,
    "brand": "Hoppe, Lynch and Bechtelar",
    "product": "Elegant Rubber Towels",
    "price": "217.00",
    "desc": "Ergonomic executive chair upholstered in bonded black leather and PVC padded seat and back for all-day comfort and support",
    "category": "Table",
    "fullName": "Zoila",
    "image": "https://loremflickr.com/640/480/clothing?lock=7192308048986112"
  },
  {
    "id": "978-1-293-82001-8",
    "color": "salmon",
    "size": ["L"],
    "rating": 3,
    "brand": "Franey - Kshlerin",
    "product": "Licensed Concrete Car",
    "price": "317.00",
    "desc": "The slim & simple Maple Gaming Keyboard from Dev Byte comes with a sleek body and 7- Color RGB LED Back-lighting for smart functionality",
    "category": "Chair",
    "fullName": "Guillermo",
    "image": "https://loremflickr.com/640/480/clothing?lock=2828396256034816"
  },
  {
    "id": "978-1-368-51728-7",
    "color": "silver",
    "size": ["XL", "L"],
    "rating": 4,
    "brand": "Shanahan - Shields",
    "product": "Refined Metal Chicken",
    "price": "289.00",
    "desc": "New ABC 13 9370, 13.3, 5th Gen CoreA5-8250U, 8GB RAM, 256GB SSD, power UHD Graphics, OS 10 Home, OS Office A & J 2016",
    "category": "Ball",
    "fullName": "Karen",
    "image": "https://loremflickr.com/640/480/clothing?lock=2742796882542592"
  },
  {
    "id": "978-1-272-71605-9",
    "color": "lime",
    "size": ["S", "M", "XL"],
    "rating": 3,
    "brand": "Nitzsche - Stokes",
    "product": "Sleek Bronze Pants",
    "price": "711.00",
    "desc": "New ABC 13 9370, 13.3, 5th Gen CoreA5-8250U, 8GB RAM, 256GB SSD, power UHD Graphics, OS 10 Home, OS Office A & J 2016",
    "category": "Chair",
    "fullName": "Myah",
    "image": "https://loremflickr.com/640/480/clothing?lock=5251530611490816"
  },
  {
    "id": "978-0-540-52064-0",
    "color": "cyan",
    "size": ["S", "M"],
    "rating": 5,
    "brand": "Huels Group",
    "product": "Awesome Plastic Mouse",
    "price": "960.00",
    "desc": "The Apollotech B340 is an affordable wireless mouse with reliable connectivity, 12 months battery life and modern design",
    "category": "Pizza",
    "fullName": "Jared",
    "image": "https://loremflickr.com/640/480/clothing?lock=3893452779552768"
  },
  {
    "id": "978-1-919332-60-4",
    "color": "turquoise",
    "size": ["M"],
    "rating": 3,
    "brand": "Jacobi Inc",
    "product": "Intelligent Granite Fish",
    "price": "247.00",
    "desc": "The automobile layout consists of a front-engine design, with transaxle-type transmissions mounted at the rear of the engine and four wheel drive",
    "category": "Table",
    "fullName": "Deron",
    "image": "https://loremflickr.com/640/480/clothing?lock=7279727920283648"
  },
  {
    "id": "978-0-475-30964-8",
    "color": "gold",
    "size": ["XL", "L", "M", "S"],
    "rating": 4,
    "brand": "Wunsch, Weber and Murphy",
    "product": "Unbranded Steel Chips",
    "price": "958.00",
    "desc": "The automobile layout consists of a front-engine design, with transaxle-type transmissions mounted at the rear of the engine and four wheel drive",
    "category": "Computer",
    "fullName": "Jovany",
    "image": "https://loremflickr.com/640/480/clothing?lock=1663693662191616"
  },
  {
    "id": "978-1-5228-3295-9",
    "color": "fuchsia",
    "size": ["M", "XL", "S", "L"],
    "rating": 2,
    "brand": "Fahey Inc",
    "product": "Practical Frozen Shirt",
    "price": "91.00",
    "desc": "The automobile layout consists of a front-engine design, with transaxle-type transmissions mounted at the rear of the engine and four wheel drive",
    "category": "Cheese",
    "fullName": "Lambert",
    "image": "https://loremflickr.com/640/480/clothing?lock=7591529059188736"
  },
  {
    "id": "978-0-233-48743-4",
    "color": "white",
    "size": ["S", "L", "XL"],
    "rating": 4,
    "brand": "Heller - Rempel",
    "product": "Electronic Granite Sausages",
    "price": "221.00",
    "desc": "Boston's most advanced compression wear technology increases muscle oxygenation, stabilizes active muscles",
    "category": "Chips",
    "fullName": "Ubaldo",
    "image": "https://loremflickr.com/640/480/clothing?lock=6582163891814400"
  },
  {
    "id": "978-0-02-856515-6",
    "color": "teal",
    "size": ["M", "XL", "L", "S"],
    "rating": 3,
    "brand": "Hartmann, Rowe and Rolfson",
    "product": "Small Concrete Tuna",
    "price": "669.00",
    "desc": "The Nagasaki Lander is the trademarked name of several series of Nagasaki sport bikes, that started with the 1984 ABC800J",
    "category": "Cheese",
    "fullName": "Amelia",
    "image": "https://loremflickr.com/640/480/clothing?lock=3276198056558592"
  },
  {
    "id": "978-1-204-51424-1",
    "color": "mint green",
    "size": ["L", "S"],
    "rating": 2,
    "brand": "Rippin - Schumm",
    "product": "Rustic Bronze Car",
    "price": "77.00",
    "desc": "Boston's most advanced compression wear technology increases muscle oxygenation, stabilizes active muscles",
    "category": "Chips",
    "fullName": "Johnnie",
    "image": "https://loremflickr.com/640/480/clothing?lock=7825961080848384"
  },
  {
    "id": "978-0-688-79955-7",
    "color": "mint green",
    "size": ["L", "M", "S"],
    "rating": 1,
    "brand": "Gleason, Ritchie and Dickinson",
    "product": "Handcrafted Fresh Table",
    "price": "1.00",
    "desc": "Carbonite web goalkeeper gloves are ergonomically designed to give easy fit",
    "category": "Ball",
    "fullName": "Maribel",
    "image": "https://loremflickr.com/640/480/clothing?lock=3024232405532672"
  },
  {
    "id": "978-0-451-28686-4",
    "color": "pink",
    "size": ["L", "S", "M", "XL"],
    "rating": 2,
    "brand": "Roob Group",
    "product": "Oriental Metal Sausages",
    "price": "123.00",
    "desc": "The Nagasaki Lander is the trademarked name of several series of Nagasaki sport bikes, that started with the 1984 ABC800J",
    "category": "Bike",
    "fullName": "Javier",
    "image": "https://loremflickr.com/640/480/clothing?lock=6742762735009792"
  },
  {
    "id": "978-1-245-20390-6",
    "color": "olive",
    "size": ["L", "M", "XL", "S"],
    "rating": 4,
    "brand": "Johnson - Bins",
    "product": "Small Granite Car",
    "price": "952.00",
    "desc": "New ABC 13 9370, 13.3, 5th Gen CoreA5-8250U, 8GB RAM, 256GB SSD, power UHD Graphics, OS 10 Home, OS Office A & J 2016",
    "category": "Chicken",
    "fullName": "Clark",
    "image": "https://loremflickr.com/640/480/clothing?lock=5094983291895808"
  }
]
